{"ocr_results":[{"text":"文革通讯","box":[[481,66],[634,66],[634,87],[481,87]]},{"text":"第30、31、32期","box":[[862,66],[1012,66],[1012,87],[862,87]]},{"text":"正确的，并据理厅了“反逆流斗争混淆阶殺陣”的。郭仁杰同志的报告，不断遭到《八·二","box":[[82,106],[1033,110],[1033,134],[82,129]]},{"text":"五》串联会的部分人打断，起哄，要求论。二个同学指出，这是无政府主义思潮泛的表現。会","box":[[82,133],[1034,137],[1034,162],[82,159]]},{"text":"后，《八·二五》貼出“老郭五·三报告糟得很，大方向錯了”等大标語，其他一些粗織針锋相对貼","box":[[82,162],[1035,163],[1035,190],[82,189]]},{"text":"了許多大标語。两派意见日超表面化、尖化。","box":[[84,191],[522,194],[522,218],[84,215]]},{"text":"来","box":[[1006,200],[1036,200],[1036,219],[1006,219]]},{"text":"該校貼出一张《徐景贤关于东方紅与新复旦师关系的指示》的大字报，暑名为“傅来之言”。此","box":[[125,220],[1036,223],[1036,247],[125,244]]},{"text":"文报道，市革委会于四月二十二日在“友谊电影院”召开一次扩大会，同济东方红代表向徐景贤告","box":[[83,249],[1033,252],[1033,276],[83,273]]},{"text":"了一状，他們七名战士給复旦打伤。徐景贤听后作了三点指示：①互相不要写大幅标語，为什么不","box":[[83,277],[1034,278],[1034,305],[83,304]]},{"text":"一起刷打刘邓标語：②互相不要去他校了，③要文斗，不要武斗。","box":[[84,306],[738,310],[738,334],[84,330]]},{"text":"复旦联絡站組准备最近串連一些工厂，高校成立批判工业上的刘邓路的联格站，内容是批判","box":[[123,336],[1033,337],[1033,361],[123,360]]},{"text":"刘、邓、薄、陳、曹等在工业上贯彻资产阶級反动路义，如象托拉斯等","box":[[79,365],[751,366],[751,390],[79,389]]},{"text":"个一出#人言","box":[[896,370],[1033,370],[1033,390],[896,390]]},{"text":"师大消息：","box":[[121,391],[216,394],[216,418],[121,415]]},{"text":"工固服牌合郑","box":[[592,400],[749,400],[749,414],[592,414]]},{"text":"气试合郑大曲","box":[[882,399],[1034,399],[1034,416],[882,416]]},{"text":"出文目前在师大校园里在对前党委書记楊西康的問题上有不同看法，一方是以數四“批判者”、物四","box":[[83,417],[1032,422],[1032,450],[83,445]]},{"text":"“紅炮兵”等为代表，为楊西康問题是严重的，应严肃批判，但与常溪萍、刘寅、张婉如之流有","box":[[93,450],[1032,451],[1032,475],[93,474]]},{"text":"区别，不属于打倒对象一方面以中文系鲁迅战斗队为代表，为杨是反革命修正主义分子，应彻底","box":[[82,477],[1036,479],[1036,506],[82,504]]},{"text":"打倒，目前双方已用小字报形式进行，估計不久将在全校开展。","box":[[81,509],[762,511],[762,532],[81,530]]},{"text":"心中#《福》念以婆","box":[[756,512],[1033,512],[1033,532],[756,532]]},{"text":"新上音：个","box":[[96,535],[308,533],[309,564],[96,566]]},{"text":"医业的众开变飞念大美市各国全","box":[[341,540],[1034,540],[1034,560],[341,560]]},{"text":"小山上海音乐学院声学系揭发批判周小燕文艺黑，周在解放前唱黄色歌曲，对洋鬼子奴颜婢膝，奉","box":[[83,558],[1037,566],[1037,603],[82,595]]},{"text":"承拍馬，俯首听命，毫无共产党員气味，把工农兵青年培养为帝修接班人。","box":[[81,599],[784,599],[784,622],[81,622]]},{"text":"云南：世个送的回氏大华半显業","box":[[97,623],[422,619],[423,646],[97,651]]},{"text":"志上出不香心宅大的区推天街出最人四","box":[[419,626],[990,626],[990,646],[419,646]]},{"text":"据悉：昆明“八·二三”（以昆明工学院为主）与毛澤东主义兵团（以云南大学为主）在进行激","box":[[124,656],[1031,656],[1031,678],[124,678]]},{"text":"烈的战。","box":[[79,682],[179,685],[178,709],[78,706]]},{"text":"面事生造总#大意一門婚","box":[[444,683],[985,683],[985,703],[444,703]]},{"text":"据悉：昆明市馬路上。有許多貼軍区导的大字报，昆明造反派为軍区某些导人值得怀疑。","box":[[123,711],[1019,711],[1019,738],[123,738]]},{"text":"青海：","box":[[125,741],[177,741],[177,764],[125,764]]},{"text":"进客国助","box":[[459,738],[662,738],[662,765],[459,765]]},{"text":"据悉：目前西宁局势已基本稳定。以刘贤权同志为首的七人軍管委員会业已組成，各项工作已走","box":[[125,770],[1030,770],[1030,793],[125,793]]},{"text":"向正规。革命派揚眉吐气，然而目前个别保皇組織仍不死心，他們假請罪、真反扑，化整为零大搞地","box":[[83,799],[1033,799],[1033,823],[83,823]]},{"text":"下活动。革命造反派和解放軍正严密注视，准备随时給予有力地反击。长：工容内主。《","box":[[83,825],[1034,830],[1034,857],[83,852]]},{"text":"西安：","box":[[126,858],[212,858],[212,879],[126,879]]},{"text":"工联出托","box":[[751,865],[842,865],[842,878],[751,878]]},{"text":"西安“联动”目前活动甚为猖，最近多次挑起武斗。深夜，常作紧急集合。目前除在西安机器","box":[[125,885],[1035,885],[1035,908],[125,908]]},{"text":"制造学校发现“联动万岁”的反动标語外，还发現所谓“联动宣言”，大叫“老子紅五类虽然犯了某","box":[[83,914],[1031,912],[1031,935],[83,937]]},{"text":"些方向性或路性錯，但本質永远是紅的”等等，拼命为氏路翻案，应当引起同志們警惕和重","box":[[84,941],[1033,940],[1033,964],[84,965]]},{"text":"视。文量而不点会革的五是回大大的命","box":[[79,970],[839,975],[839,999],[79,994]]},{"text":"还庆","box":[[968,979],[1031,979],[1031,996],[968,996]]},{"text":"广西：","box":[[124,998],[179,998],[179,1023],[124,1023]]},{"text":"由南宁市革命造反派粗織起来的“四·二二”革命行动火指部主办的“四·二二”战报，","box":[[126,1025],[1023,1022],[1023,1049],[126,1052]]},{"text":"最近发表一篇题为《新生的<广西日报>是什么货色！》的文章，怒指出《广西日报》已充当了党","box":[[83,1056],[1034,1053],[1034,1077],[83,1080]]},{"text":"内一小走资本主义道路的当权派的御用工具，明显为資产阶复辟摇旗呐喊，开道。","box":[[85,1086],[936,1082],[936,1106],[85,1110]]},{"text":"命四月二十日起，南宁市革命众，包括工人、农民、学生、解放軍在大街小巷粉粉游行示威，","box":[[107,1115],[1017,1111],[1017,1134],[107,1138]]},{"text":"这一革命行动已得到桂林、柳州、梧州的广大革命造反派支持。","box":[[83,1146],[675,1144],[675,1165],[83,1167]]},{"text":"115","box":[[687,1153],[704,1153],[704,1160],[687,1160]]},{"text":"会富","box":[[993,1152],[1028,1152],[1028,1163],[993,1163]]},{"text":"A二十二日起，广西紅卫兵組在《广西日报》社門前静坐示威。据悉五月二日下午七时，紅卫","box":[[129,1173],[1033,1169],[1033,1192],[129,1197]]},{"text":"兵組織已根据中央来电指示，曹时撤退。","box":[[85,1204],[464,1201],[464,1221],[85,1223]]},{"text":"《#怕妹》","box":[[455,1203],[600,1207],[600,1224],[454,1220]]},{"text":"三日，各革命組織根据中央指示精神派出代表赴京，竞遭到保守派圍攻，打伤三人，火車推迟","box":[[129,1229],[1033,1225],[1033,1248],[129,1252]]},{"text":"至三时半才开出，点三个多小时，广西情况正在发展中。","box":[[84,1258],[634,1256],[634,1280],[84,1282]]},{"text":"山东：","box":[[129,1291],[179,1291],[179,1314],[129,1314]]},{"text":"A五月六日晚八时，山东煤矿学院红卫兵红旗公社、山东师范学院文革串連指部革命小将及山","box":[[129,1318],[1034,1314],[1034,1338],[129,1342]]},{"text":"东革命工人总指部部分革命工人，开进并包圍了近两天来制造反革命事件的司分部国棉三厂。敌人","box":[[85,1348],[1034,1342],[1034,1365],[85,1371]]},{"text":"负隅顽抗，打伤乘車先去的煤矿学院革命同学。但在我强大的攻势下，敌人終于落罔就擒，：二个个被","box":[[86,1377],[1036,1371],[1036,1394],[86,1400]]},{"text":"揪出。","box":[[85,1407],[140,1407],[140,1429],[85,1429]]},{"text":"五月七日上午，在国棉三厂举行了声势浩大的控斗争大会。并把由省革命委員会抓住的三厂","box":[[129,1434],[1034,1427],[1034,1450],[129,1458]]},{"text":"“革委会”負责人，制造反革命事件的罪魁首王德敏拉来示众。省公安厅根据广大众要求，将反","box":[[92,1463],[1035,1455],[1035,1478],[92,1485]]},{"text":"199900","box":[[872,1531],[990,1533],[990,1553],[872,1551]]}],"dimensions":{"height":1594,"width":1143}}